{
  "features": [
    {
      "geometry": {
        "coordinates": [
          14.424509929190064,
          50.110733674365314
        ],
        "type": "Point"
      },
      "properties": {
        "amenity": "vending_machine",
        "source": "opendata.praha.eu",
        "vending": "parking_tickets"
      },
      "type": "Feature"
    },
    {
      "geometry": {
        "coordinates": [
          14.420647035148646,
          50.11073589982079
        ],
        "type": "Point"
      },
      "properties": {
        "amenity": "vending_machine",
        "source": "opendata.praha.eu",
        "vending": "parking_tickets"
      },
      "type": "Feature"
    },
    {
      "geometry": {
        "coordinates": [
          14.418087372806015,
          50.110744147397185
        ],
        "type": "Point"
      },
      "properties": {
        "amenity": "vending_machine",
        "source": "opendata.praha.eu",
        "vending": "parking_tickets"
      },
      "type": "Feature"
    }
  ],
  "type": "FeatureCollection"
}